{
  "name" : "B - Booby Prize",
  "testType" : "SINGLE",
  "input" : {
    "type" : "STANDARD",
    "fileName" : "input.txt"
  },
  "output" : {
    "type" : "STANDARD",
    "fileName" : "output.txt"
  },
  "tests" : [ {
    "input" : "6\n1 123 12345 12 1234 123456\n",
    "output" : "3\n",
    "index" : 0,
    "active" : true
  }, {
    "input" : "5\n3 1 4 15 9\n",
    "output" : "5\n",
    "index" : 1,
    "active" : true
  } ],
  "location" : "src/atcoder",
  "vmArgs" : "-Xmx1024M",
  "mainClass" : "Main",
  "taskClass" : "atcoder.BBoobyPrize",
  "checkerClass" : "net.egork.chelper.checkers.TokenChecker",
  "checkerParameters" : "",
  "testClasses" : [ ],
  "date" : "2021.08.08",
  "contestName" : "AtCoder - AtCoder Beginner Contest 213",
  "truncate" : true,
  "inputClass" : "tool.FastReader",
  "outputClass" : "java.io.PrintWriter",
  "includeLocale" : false,
  "failOnOverflow" : false,
  "interactive" : false,
  "interactor" : "net.egork.chelper.tester.Interactor"
}